contexere/__init__.py
contexere/discover.py
contexere/logbook.py
contexere/name.py
contexere/scheme.py
contexere-0.5.dist-info/LICENSE.txt
contexere-0.5.dist-info/METADATA
contexere-0.5.dist-info/WHEEL
contexere-0.5.dist-info/entry_points.txt
contexere-0.5.dist-info/top_level.txt
contexere-0.5.dist-info/RECORD
