Metadata-Version: 2.1
Name: contexere
Version: 0.5
Summary: Add a short description here!
Home-page: https://github.com/kempa-liehr/contexere/
Author: Andreas Kempa-Liehr
Author-email: kempa-liehr@protonmail.com
License: MIT
Platform: any
Classifier: Development Status :: 4 - Beta
Classifier: Programming Language :: Python
License-File: LICENSE.txt
Requires-Dist: pandas
Requires-Dist: pytz
Requires-Dist: tzlocal
Provides-Extra: testing
Requires-Dist: setuptools ; extra == 'testing'
Requires-Dist: pytest ; extra == 'testing'
Requires-Dist: pytest-cov ; extra == 'testing'
